LICENSE.txt
MANIFEST.in
README.rst
VERSION
requirements-test.txt
requirements.txt
setup.py
django_ssl_auth/__init__.py
django_ssl_auth/base.py
django_ssl_auth/fineid.py
django_ssl_auth.egg-info/PKG-INFO
django_ssl_auth.egg-info/SOURCES.txt
django_ssl_auth.egg-info/dependency_links.txt
django_ssl_auth.egg-info/not-zip-safe
django_ssl_auth.egg-info/requires.txt
django_ssl_auth.egg-info/top_level.txt