Metadata-Version: 1.1
Name: django-ssl-auth
Version: 2.0.1
Summary: Django SSL Client Authentication
Home-page: https://github.com/tarkatronic/django-ssl-auth/
Author: Joey Wilhelm
Author-email: tarkatronic@gmail.com
License: MIT
Download-URL: https://github.com/tarkatronic/django-ssl-auth/archive/master.tar.gz
Platform: UNKNOWN
Classifier: Development Status :: 5 - Production/Stable
Classifier: Environment :: Web Environment
Classifier: Intended Audience :: Developers
Classifier: License :: OSI Approved :: MIT License
Classifier: Natural Language :: English
Classifier: Operating System :: OS Independent
Classifier: Programming Language :: Python
Classifier: Programming Language :: Python :: 2.7
Classifier: Programming Language :: Python :: 3
Classifier: Programming Language :: Python :: 3.3
Classifier: Programming Language :: Python :: 3.4
Classifier: Programming Language :: Python :: 3.5
Classifier: Programming Language :: Python :: 3.6
Classifier: Framework :: Django
Classifier: Framework :: Django :: 1.8
Classifier: Framework :: Django :: 1.9
Classifier: Framework :: Django :: 1.10
Classifier: Framework :: Django :: 1.11
Classifier: Topic :: Software Development :: Libraries :: Python Modules
